{"surah": 114, "summary": "Surah An-Nas seeks refuge in the Lord, King, and God of mankind from the whisperer who withdraws—who whispers into hearts—from among jinn and men.", "ayah_connections": [{"source_key": "114:1", "groups": [{"title": "Section: Seek refuge in the Lord, King, and God of mankind from the whispering retreating tempter among jinn and men", "links": []}, {"title": "Allah", "links": [{"target_key": "1:1", "note": "Linked via topic: Allah"}, {"target_key": "1:2", "note": "Linked via topic: Allah"}, {"target_key": "1:6", "note": "Linked via topic: Allah"}, {"target_key": "1:7", "note": "Linked via topic: Allah"}, {"target_key": "2:7", "note": "Linked via topic: Allah"}, {"target_key": "2:8", "note": "Linked via topic: Allah"}, {"target_key": "2:9", "note": "Linked via topic: Allah"}, {"target_key": "2:10", "note": "Linked via topic: Allah"}, {"target_key": "2:15", "note": "Linked via topic: Allah"}, {"target_key": "2:17", "note": "Linked via topic: Allah"}, {"target_key": "2:19", "note": "Linked via topic: Allah"}, {"target_key": "2:22", "note": "Linked via topic: Allah"}, {"target_key": "2:23", "note": "Linked via topic: Allah"}, {"target_key": "2:28", "note": "Linked via topic: Allah"}, {"target_key": "2:26", "note": "Linked via topic: Allah"}]}, {"title": "Jinn", "links": [{"target_key": "6:112", "note": "Linked via topic: Jinn"}, {"target_key": "6:128", "note": "Linked via topic: Jinn"}, {"target_key": "6:130", "note": "Linked via topic: Jinn"}, {"target_key": "7:179", "note": "Linked via topic: Jinn"}, {"target_key": "11:119", "note": "Linked via topic: Jinn"}, {"target_key": "15:27", "note": "Linked via topic: Jinn"}, {"target_key": "18:50", "note": "Linked via topic: Jinn"}, {"target_key": "27:17", "note": "Linked via topic: Jinn"}, {"target_key": "32:13", "note": "Linked via topic: Jinn"}, {"target_key": "34:12", "note": "Linked via topic: Jinn"}, {"target_key": "34:14", "note": "Linked via topic: Jinn"}, {"target_key": "34:41", "note": "Linked via topic: Jinn"}, {"target_key": "46:18", "note": "Linked via topic: Jinn"}, {"target_key": "46:29", "note": "Linked via topic: Jinn"}, {"target_key": "51:56", "note": "Linked via topic: Jinn"}]}, {"title": "refuge from evil with", "links": [{"target_key": "113:1", "note": "Linked via topic: refuge from evil with"}, {"target_key": "113:2", "note": "Linked via topic: refuge from evil with"}, {"target_key": "113:3", "note": "Linked via topic: refuge from evil with"}, {"target_key": "113:4", "note": "Linked via topic: refuge from evil with"}, {"target_key": "113:5", "note": "Linked via topic: refuge from evil with"}, {"target_key": "114:2", "note": "Linked via topic: refuge from evil with"}, {"target_key": "114:3", "note": "Linked via topic: refuge from evil with"}, {"target_key": "114:4", "note": "Linked via topic: refuge from evil with"}, {"target_key": "114:5", "note": "Linked via topic: refuge from evil with"}, {"target_key": "114:6", "note": "Linked via topic: refuge from evil with"}]}, {"title": "Protection", "links": [{"target_key": "3:36", "note": "Linked via topic: Protection"}, {"target_key": "4:34", "note": "Linked via topic: Protection"}, {"target_key": "5:41", "note": "Linked via topic: Protection"}, {"target_key": "7:196", "note": "Linked via topic: Protection"}, {"target_key": "9:6", "note": "Linked via topic: Protection"}, {"target_key": "9:8", "note": "Linked via topic: Protection"}, {"target_key": "9:10", "note": "Linked via topic: Protection"}, {"target_key": "11:47", "note": "Linked via topic: Protection"}, {"target_key": "16:98", "note": "Linked via topic: Protection"}, {"target_key": "18:44", "note": "Linked via topic: Protection"}, {"target_key": "19:81", "note": "Linked via topic: Protection"}, {"target_key": "23:97", "note": "Linked via topic: Protection"}, {"target_key": "23:98", "note": "Linked via topic: Protection"}, {"target_key": "33:13", "note": "Linked via topic: Protection"}, {"target_key": "37:7", "note": "Linked via topic: Protection"}]}, {"title": "Faith", "links": []}, {"title": "Worship", "links": []}, {"title": "Family", "links": []}, {"title": "Halal", "links": []}]}, {"source_key": "114:2", "groups": [{"title": "Section: Seek refuge in the Lord, King, and God of mankind from the whispering retreating tempter among jinn and men", "links": []}, {"title": "Allah", "links": [{"target_key": "1:1", "note": "Linked via topic: Allah"}, {"target_key": "1:2", "note": "Linked via topic: Allah"}, {"target_key": "1:6", "note": "Linked via topic: Allah"}, {"target_key": "1:7", "note": "Linked via topic: Allah"}, {"target_key": "2:7", "note": "Linked via topic: Allah"}, {"target_key": "2:8", "note": "Linked via topic: Allah"}, {"target_key": "2:9", "note": "Linked via topic: Allah"}, {"target_key": "2:10", "note": "Linked via topic: Allah"}, {"target_key": "2:15", "note": "Linked via topic: Allah"}, {"target_key": "2:17", "note": "Linked via topic: Allah"}, {"target_key": "2:19", "note": "Linked via topic: Allah"}, {"target_key": "2:22", "note": "Linked via topic: Allah"}, {"target_key": "2:23", "note": "Linked via topic: Allah"}, {"target_key": "2:28", "note": "Linked via topic: Allah"}, {"target_key": "2:26", "note": "Linked via topic: Allah"}]}, {"title": "King", "links": [{"target_key": "12:43", "note": "Linked via topic: King"}, {"target_key": "12:50", "note": "Linked via topic: King"}, {"target_key": "12:54", "note": "Linked via topic: King"}, {"target_key": "12:72", "note": "Linked via topic: King"}, {"target_key": "23:116", "note": "Linked via topic: King"}, {"target_key": "27:34", "note": "Linked via topic: King"}, {"target_key": "59:23", "note": "Linked via topic: King"}, {"target_key": "5:20", "note": "Linked via topic: King"}, {"target_key": "20:114", "note": "Linked via topic: King"}, {"target_key": "2:247", "note": "Linked via topic: King"}, {"target_key": "2:248", "note": "Linked via topic: King"}, {"target_key": "2:251", "note": "Linked via topic: King"}, {"target_key": "25:2", "note": "Linked via topic: King"}, {"target_key": "2:246", "note": "Linked via topic: King"}, {"target_key": "12:76", "note": "Linked via topic: King"}]}, {"title": "Jinn", "links": [{"target_key": "6:112", "note": "Linked via topic: Jinn"}, {"target_key": "6:128", "note": "Linked via topic: Jinn"}, {"target_key": "6:130", "note": "Linked via topic: Jinn"}, {"target_key": "7:179", "note": "Linked via topic: Jinn"}, {"target_key": "11:119", "note": "Linked via topic: Jinn"}, {"target_key": "15:27", "note": "Linked via topic: Jinn"}, {"target_key": "18:50", "note": "Linked via topic: Jinn"}, {"target_key": "27:17", "note": "Linked via topic: Jinn"}, {"target_key": "32:13", "note": "Linked via topic: Jinn"}, {"target_key": "34:12", "note": "Linked via topic: Jinn"}, {"target_key": "34:14", "note": "Linked via topic: Jinn"}, {"target_key": "34:41", "note": "Linked via topic: Jinn"}, {"target_key": "46:18", "note": "Linked via topic: Jinn"}, {"target_key": "46:29", "note": "Linked via topic: Jinn"}, {"target_key": "51:56", "note": "Linked via topic: Jinn"}]}, {"title": "refuge from evil with", "links": [{"target_key": "113:1", "note": "Linked via topic: refuge from evil with"}, {"target_key": "113:2", "note": "Linked via topic: refuge from evil with"}, {"target_key": "113:3", "note": "Linked via topic: refuge from evil with"}, {"target_key": "113:4", "note": "Linked via topic: refuge from evil with"}, {"target_key": "113:5", "note": "Linked via topic: refuge from evil with"}, {"target_key": "114:1", "note": "Linked via topic: refuge from evil with"}, {"target_key": "114:3", "note": "Linked via topic: refuge from evil with"}, {"target_key": "114:4", "note": "Linked via topic: refuge from evil with"}, {"target_key": "114:5", "note": "Linked via topic: refuge from evil with"}, {"target_key": "114:6", "note": "Linked via topic: refuge from evil with"}]}, {"title": "Faith", "links": []}, {"title": "Worship", "links": []}, {"title": "Family", "links": []}]}, {"source_key": "114:3", "groups": [{"title": "Section: Seek refuge in the Lord, King, and God of mankind from the whispering retreating tempter among jinn and men", "links": []}, {"title": "Allah", "links": [{"target_key": "1:1", "note": "Linked via topic: Allah"}, {"target_key": "1:2", "note": "Linked via topic: Allah"}, {"target_key": "1:6", "note": "Linked via topic: Allah"}, {"target_key": "1:7", "note": "Linked via topic: Allah"}, {"target_key": "2:7", "note": "Linked via topic: Allah"}, {"target_key": "2:8", "note": "Linked via topic: Allah"}, {"target_key": "2:9", "note": "Linked via topic: Allah"}, {"target_key": "2:10", "note": "Linked via topic: Allah"}, {"target_key": "2:15", "note": "Linked via topic: Allah"}, {"target_key": "2:17", "note": "Linked via topic: Allah"}, {"target_key": "2:19", "note": "Linked via topic: Allah"}, {"target_key": "2:22", "note": "Linked via topic: Allah"}, {"target_key": "2:23", "note": "Linked via topic: Allah"}, {"target_key": "2:28", "note": "Linked via topic: Allah"}, {"target_key": "2:26", "note": "Linked via topic: Allah"}]}, {"title": "Jinn", "links": [{"target_key": "6:112", "note": "Linked via topic: Jinn"}, {"target_key": "6:128", "note": "Linked via topic: Jinn"}, {"target_key": "6:130", "note": "Linked via topic: Jinn"}, {"target_key": "7:179", "note": "Linked via topic: Jinn"}, {"target_key": "11:119", "note": "Linked via topic: Jinn"}, {"target_key": "15:27", "note": "Linked via topic: Jinn"}, {"target_key": "18:50", "note": "Linked via topic: Jinn"}, {"target_key": "27:17", "note": "Linked via topic: Jinn"}, {"target_key": "32:13", "note": "Linked via topic: Jinn"}, {"target_key": "34:12", "note": "Linked via topic: Jinn"}, {"target_key": "34:14", "note": "Linked via topic: Jinn"}, {"target_key": "34:41", "note": "Linked via topic: Jinn"}, {"target_key": "46:18", "note": "Linked via topic: Jinn"}, {"target_key": "46:29", "note": "Linked via topic: Jinn"}, {"target_key": "51:56", "note": "Linked via topic: Jinn"}]}, {"title": "refuge from evil with", "links": [{"target_key": "113:1", "note": "Linked via topic: refuge from evil with"}, {"target_key": "113:2", "note": "Linked via topic: refuge from evil with"}, {"target_key": "113:3", "note": "Linked via topic: refuge from evil with"}, {"target_key": "113:4", "note": "Linked via topic: refuge from evil with"}, {"target_key": "113:5", "note": "Linked via topic: refuge from evil with"}, {"target_key": "114:1", "note": "Linked via topic: refuge from evil with"}, {"target_key": "114:2", "note": "Linked via topic: refuge from evil with"}, {"target_key": "114:4", "note": "Linked via topic: refuge from evil with"}, {"target_key": "114:5", "note": "Linked via topic: refuge from evil with"}, {"target_key": "114:6", "note": "Linked via topic: refuge from evil with"}]}, {"title": "Faith", "links": []}, {"title": "Family", "links": []}]}, {"source_key": "114:4", "groups": [{"title": "Section: Seek refuge in the Lord, King, and God of mankind from the whispering retreating tempter among jinn and men", "links": []}, {"title": "Allah", "links": [{"target_key": "1:1", "note": "Linked via topic: Allah"}, {"target_key": "1:2", "note": "Linked via topic: Allah"}, {"target_key": "1:6", "note": "Linked via topic: Allah"}, {"target_key": "1:7", "note": "Linked via topic: Allah"}, {"target_key": "2:7", "note": "Linked via topic: Allah"}, {"target_key": "2:8", "note": "Linked via topic: Allah"}, {"target_key": "2:9", "note": "Linked via topic: Allah"}, {"target_key": "2:10", "note": "Linked via topic: Allah"}, {"target_key": "2:15", "note": "Linked via topic: Allah"}, {"target_key": "2:17", "note": "Linked via topic: Allah"}, {"target_key": "2:19", "note": "Linked via topic: Allah"}, {"target_key": "2:22", "note": "Linked via topic: Allah"}, {"target_key": "2:23", "note": "Linked via topic: Allah"}, {"target_key": "2:28", "note": "Linked via topic: Allah"}, {"target_key": "2:26", "note": "Linked via topic: Allah"}]}, {"title": "Jinn", "links": [{"target_key": "6:112", "note": "Linked via topic: Jinn"}, {"target_key": "6:128", "note": "Linked via topic: Jinn"}, {"target_key": "6:130", "note": "Linked via topic: Jinn"}, {"target_key": "7:179", "note": "Linked via topic: Jinn"}, {"target_key": "11:119", "note": "Linked via topic: Jinn"}, {"target_key": "15:27", "note": "Linked via topic: Jinn"}, {"target_key": "18:50", "note": "Linked via topic: Jinn"}, {"target_key": "27:17", "note": "Linked via topic: Jinn"}, {"target_key": "32:13", "note": "Linked via topic: Jinn"}, {"target_key": "34:12", "note": "Linked via topic: Jinn"}, {"target_key": "34:14", "note": "Linked via topic: Jinn"}, {"target_key": "34:41", "note": "Linked via topic: Jinn"}, {"target_key": "46:18", "note": "Linked via topic: Jinn"}, {"target_key": "46:29", "note": "Linked via topic: Jinn"}, {"target_key": "51:56", "note": "Linked via topic: Jinn"}]}, {"title": "refuge from evil with", "links": [{"target_key": "113:1", "note": "Linked via topic: refuge from evil with"}, {"target_key": "113:2", "note": "Linked via topic: refuge from evil with"}, {"target_key": "113:3", "note": "Linked via topic: refuge from evil with"}, {"target_key": "113:4", "note": "Linked via topic: refuge from evil with"}, {"target_key": "113:5", "note": "Linked via topic: refuge from evil with"}, {"target_key": "114:1", "note": "Linked via topic: refuge from evil with"}, {"target_key": "114:2", "note": "Linked via topic: refuge from evil with"}, {"target_key": "114:3", "note": "Linked via topic: refuge from evil with"}, {"target_key": "114:5", "note": "Linked via topic: refuge from evil with"}, {"target_key": "114:6", "note": "Linked via topic: refuge from evil with"}]}, {"title": "Faith", "links": []}, {"title": "Character", "links": []}, {"title": "Society", "links": []}, {"title": "Finance", "links": []}, {"title": "Warnings", "links": []}, {"title": "Justice", "links": []}]}, {"source_key": "114:5", "groups": [{"title": "Section: Seek refuge in the Lord, King, and God of mankind from the whispering retreating tempter among jinn and men", "links": []}, {"title": "Allah", "links": [{"target_key": "1:1", "note": "Linked via topic: Allah"}, {"target_key": "1:2", "note": "Linked via topic: Allah"}, {"target_key": "1:6", "note": "Linked via topic: Allah"}, {"target_key": "1:7", "note": "Linked via topic: Allah"}, {"target_key": "2:7", "note": "Linked via topic: Allah"}, {"target_key": "2:8", "note": "Linked via topic: Allah"}, {"target_key": "2:9", "note": "Linked via topic: Allah"}, {"target_key": "2:10", "note": "Linked via topic: Allah"}, {"target_key": "2:15", "note": "Linked via topic: Allah"}, {"target_key": "2:17", "note": "Linked via topic: Allah"}, {"target_key": "2:19", "note": "Linked via topic: Allah"}, {"target_key": "2:22", "note": "Linked via topic: Allah"}, {"target_key": "2:23", "note": "Linked via topic: Allah"}, {"target_key": "2:28", "note": "Linked via topic: Allah"}, {"target_key": "2:26", "note": "Linked via topic: Allah"}]}, {"title": "Jinn", "links": [{"target_key": "6:112", "note": "Linked via topic: Jinn"}, {"target_key": "6:128", "note": "Linked via topic: Jinn"}, {"target_key": "6:130", "note": "Linked via topic: Jinn"}, {"target_key": "7:179", "note": "Linked via topic: Jinn"}, {"target_key": "11:119", "note": "Linked via topic: Jinn"}, {"target_key": "15:27", "note": "Linked via topic: Jinn"}, {"target_key": "18:50", "note": "Linked via topic: Jinn"}, {"target_key": "27:17", "note": "Linked via topic: Jinn"}, {"target_key": "32:13", "note": "Linked via topic: Jinn"}, {"target_key": "34:12", "note": "Linked via topic: Jinn"}, {"target_key": "34:14", "note": "Linked via topic: Jinn"}, {"target_key": "34:41", "note": "Linked via topic: Jinn"}, {"target_key": "46:18", "note": "Linked via topic: Jinn"}, {"target_key": "46:29", "note": "Linked via topic: Jinn"}, {"target_key": "51:56", "note": "Linked via topic: Jinn"}]}, {"title": "refuge from evil with", "links": [{"target_key": "113:1", "note": "Linked via topic: refuge from evil with"}, {"target_key": "113:2", "note": "Linked via topic: refuge from evil with"}, {"target_key": "113:3", "note": "Linked via topic: refuge from evil with"}, {"target_key": "113:4", "note": "Linked via topic: refuge from evil with"}, {"target_key": "113:5", "note": "Linked via topic: refuge from evil with"}, {"target_key": "114:1", "note": "Linked via topic: refuge from evil with"}, {"target_key": "114:2", "note": "Linked via topic: refuge from evil with"}, {"target_key": "114:3", "note": "Linked via topic: refuge from evil with"}, {"target_key": "114:4", "note": "Linked via topic: refuge from evil with"}, {"target_key": "114:6", "note": "Linked via topic: refuge from evil with"}]}, {"title": "Faith", "links": []}, {"title": "Warnings", "links": []}, {"title": "Hereafter", "links": []}, {"title": "Justice", "links": []}]}, {"source_key": "114:6", "groups": [{"title": "Section: Seek refuge in the Lord, King, and God of mankind from the whispering retreating tempter among jinn and men", "links": []}, {"title": "Allah", "links": [{"target_key": "1:1", "note": "Linked via topic: Allah"}, {"target_key": "1:2", "note": "Linked via topic: Allah"}, {"target_key": "1:6", "note": "Linked via topic: Allah"}, {"target_key": "1:7", "note": "Linked via topic: Allah"}, {"target_key": "2:7", "note": "Linked via topic: Allah"}, {"target_key": "2:8", "note": "Linked via topic: Allah"}, {"target_key": "2:9", "note": "Linked via topic: Allah"}, {"target_key": "2:10", "note": "Linked via topic: Allah"}, {"target_key": "2:15", "note": "Linked via topic: Allah"}, {"target_key": "2:17", "note": "Linked via topic: Allah"}, {"target_key": "2:19", "note": "Linked via topic: Allah"}, {"target_key": "2:22", "note": "Linked via topic: Allah"}, {"target_key": "2:23", "note": "Linked via topic: Allah"}, {"target_key": "2:28", "note": "Linked via topic: Allah"}, {"target_key": "2:26", "note": "Linked via topic: Allah"}]}, {"title": "Paradise", "links": [{"target_key": "2:35", "note": "Linked via topic: Paradise"}, {"target_key": "2:82", "note": "Linked via topic: Paradise"}, {"target_key": "2:111", "note": "Linked via topic: Paradise"}, {"target_key": "2:214", "note": "Linked via topic: Paradise"}, {"target_key": "2:221", "note": "Linked via topic: Paradise"}, {"target_key": "3:133", "note": "Linked via topic: Paradise"}, {"target_key": "3:185", "note": "Linked via topic: Paradise"}, {"target_key": "4:124", "note": "Linked via topic: Paradise"}, {"target_key": "5:72", "note": "Linked via topic: Paradise"}, {"target_key": "7:19", "note": "Linked via topic: Paradise"}, {"target_key": "7:22", "note": "Linked via topic: Paradise"}, {"target_key": "7:27", "note": "Linked via topic: Paradise"}, {"target_key": "7:40", "note": "Linked via topic: Paradise"}, {"target_key": "7:43", "note": "Linked via topic: Paradise"}, {"target_key": "7:44", "note": "Linked via topic: Paradise"}]}, {"title": "Jinn", "links": [{"target_key": "6:112", "note": "Linked via topic: Jinn"}, {"target_key": "6:128", "note": "Linked via topic: Jinn"}, {"target_key": "6:130", "note": "Linked via topic: Jinn"}, {"target_key": "7:179", "note": "Linked via topic: Jinn"}, {"target_key": "11:119", "note": "Linked via topic: Jinn"}, {"target_key": "15:27", "note": "Linked via topic: Jinn"}, {"target_key": "18:50", "note": "Linked via topic: Jinn"}, {"target_key": "27:17", "note": "Linked via topic: Jinn"}, {"target_key": "32:13", "note": "Linked via topic: Jinn"}, {"target_key": "34:12", "note": "Linked via topic: Jinn"}, {"target_key": "34:14", "note": "Linked via topic: Jinn"}, {"target_key": "34:41", "note": "Linked via topic: Jinn"}, {"target_key": "46:18", "note": "Linked via topic: Jinn"}, {"target_key": "46:29", "note": "Linked via topic: Jinn"}, {"target_key": "51:56", "note": "Linked via topic: Jinn"}]}, {"title": "refuge from evil with", "links": [{"target_key": "113:1", "note": "Linked via topic: refuge from evil with"}, {"target_key": "113:2", "note": "Linked via topic: refuge from evil with"}, {"target_key": "113:3", "note": "Linked via topic: refuge from evil with"}, {"target_key": "113:4", "note": "Linked via topic: refuge from evil with"}, {"target_key": "113:5", "note": "Linked via topic: refuge from evil with"}, {"target_key": "114:1", "note": "Linked via topic: refuge from evil with"}, {"target_key": "114:2", "note": "Linked via topic: refuge from evil with"}, {"target_key": "114:3", "note": "Linked via topic: refuge from evil with"}, {"target_key": "114:4", "note": "Linked via topic: refuge from evil with"}, {"target_key": "114:5", "note": "Linked via topic: refuge from evil with"}]}, {"title": "Heaven", "links": [{"target_key": "2:25", "note": "Linked via topic: Heaven"}, {"target_key": "3:15", "note": "Linked via topic: Heaven"}, {"target_key": "3:136", "note": "Linked via topic: Heaven"}, {"target_key": "3:181", "note": "Linked via topic: Heaven"}, {"target_key": "3:195", "note": "Linked via topic: Heaven"}, {"target_key": "3:198", "note": "Linked via topic: Heaven"}, {"target_key": "2:35", "note": "Linked via topic: Heaven"}, {"target_key": "2:82", "note": "Linked via topic: Heaven"}, {"target_key": "2:111", "note": "Linked via topic: Heaven"}, {"target_key": "2:214", "note": "Linked via topic: Heaven"}, {"target_key": "2:221", "note": "Linked via topic: Heaven"}, {"target_key": "2:265", "note": "Linked via topic: Heaven"}, {"target_key": "2:266", "note": "Linked via topic: Heaven"}, {"target_key": "3:133", "note": "Linked via topic: Heaven"}, {"target_key": "3:142", "note": "Linked via topic: Heaven"}]}, {"title": "Faith", "links": []}, {"title": "Warnings", "links": []}]}]}